{
  "clang --threads 4": {
    "execute": {
      "clocks": [
        {
          "run": 9098,
          "values": [
            7853
          ]
        },
        {
          "run": 9162,
          "values": [
            7853
          ]
        },
        {
          "run": 9226,
          "values": [
            7853
          ]
        },
        {
          "run": 9290,
          "values": [
            7853
          ]
        },
        {
          "run": 9354,
          "values": [
            7853
          ]
        },
        {
          "run": 9418,
          "values": [
            7853
          ]
        }
      ],
      "cpu": [
        {
          "run": 9098,
          "values": [
            4.62
          ]
        },
        {
          "run": 9162,
          "values": [
            4.59
          ]
        },
        {
          "run": 9226,
          "values": [
            4.56
          ]
        },
        {
          "run": 9290,
          "values": [
            4.62
          ]
        },
        {
          "run": 9354,
          "values": [
            5.12
          ]
        },
        {
          "run": 9418,
          "values": [
            5.16
          ]
        }
      ],
      "elapsed": [
        {
          "run": 9098,
          "values": [
            1.17
          ]
        },
        {
          "run": 9162,
          "values": [
            1.16
          ]
        },
        {
          "run": 9226,
          "values": [
            1.15
          ]
        },
        {
          "run": 9290,
          "values": [
            1.17
          ]
        },
        {
          "run": 9354,
          "values": [
            1.29
          ]
        },
        {
          "run": 9418,
          "values": [
            1.3
          ]
        }
      ],
      "memory": [
        {
          "run": 9098,
          "values": [
            14.236
          ]
        },
        {
          "run": 9162,
          "values": [
            14.184000000000001
          ]
        },
        {
          "run": 9226,
          "values": [
            14.296000000000001
          ]
        },
        {
          "run": 9290,
          "values": [
            14.348
          ]
        },
        {
          "run": 9354,
          "values": [
            14.076
          ]
        },
        {
          "run": 9418,
          "values": [
            14.22
          ]
        }
      ],
      "speed": [
        {
          "run": 9098,
          "values": [
            6.711965811965812
          ]
        },
        {
          "run": 9162,
          "values": [
            6.769827586206897
          ]
        },
        {
          "run": 9226,
          "values": [
            6.828695652173914
          ]
        },
        {
          "run": 9290,
          "values": [
            6.711965811965812
          ]
        },
        {
          "run": 9354,
          "values": [
            6.087596899224806
          ]
        },
        {
          "run": 9418,
          "values": [
            6.0407692307692304
          ]
        }
      ],
      "system": [
        {
          "run": 9098,
          "values": [
            0.01
          ]
        },
        {
          "run": 9162,
          "values": [
            0.01
          ]
        },
        {
          "run": 9226,
          "values": [
            0.01
          ]
        },
        {
          "run": 9290,
          "values": [
            0.01
          ]
        },
        {
          "run": 9354,
          "values": [
            0.01
          ]
        },
        {
          "run": 9418,
          "values": [
            0.01
          ]
        }
      ],
      "user": [
        {
          "run": 9098,
          "values": [
            4.62
          ]
        },
        {
          "run": 9162,
          "values": [
            4.59
          ]
        },
        {
          "run": 9226,
          "values": [
            4.56
          ]
        },
        {
          "run": 9290,
          "values": [
            4.62
          ]
        },
        {
          "run": 9354,
          "values": [
            5.12
          ]
        },
        {
          "run": 9418,
          "values": [
            5.16
          ]
        }
      ]
    }
  },
  "gcc": {
    "execute": {
      "clocks": [
        {
          "run": 9136,
          "values": [
            7853
          ]
        },
        {
          "run": 9200,
          "values": [
            7853
          ]
        },
        {
          "run": 9264,
          "values": [
            7853
          ]
        },
        {
          "run": 9328,
          "values": [
            7853
          ]
        },
        {
          "run": 9392,
          "values": [
            7853
          ]
        },
        {
          "run": 9456,
          "values": [
            7853
          ]
        }
      ],
      "cpu": [
        {
          "run": 9136,
          "values": [
            2.56
          ]
        },
        {
          "run": 9200,
          "values": [
            2.55
          ]
        },
        {
          "run": 9264,
          "values": [
            2.56
          ]
        },
        {
          "run": 9328,
          "values": [
            1.75
          ]
        },
        {
          "run": 9392,
          "values": [
            2.58
          ]
        },
        {
          "run": 9456,
          "values": [
            2.56
          ]
        }
      ],
      "elapsed": [
        {
          "run": 9136,
          "values": [
            2.56
          ]
        },
        {
          "run": 9200,
          "values": [
            2.55
          ]
        },
        {
          "run": 9264,
          "values": [
            2.56
          ]
        },
        {
          "run": 9328,
          "values": [
            1.75
          ]
        },
        {
          "run": 9392,
          "values": [
            2.58
          ]
        },
        {
          "run": 9456,
          "values": [
            2.57
          ]
        }
      ],
      "memory": [
        {
          "run": 9136,
          "values": [
            12.96
          ]
        },
        {
          "run": 9200,
          "values": [
            12.82
          ]
        },
        {
          "run": 9264,
          "values": [
            13.032
          ]
        },
        {
          "run": 9328,
          "values": [
            13.088000000000001
          ]
        },
        {
          "run": 9392,
          "values": [
            12.868
          ]
        },
        {
          "run": 9456,
          "values": [
            13.048
          ]
        }
      ],
      "speed": [
        {
          "run": 9136,
          "values": [
            3.067578125
          ]
        },
        {
          "run": 9200,
          "values": [
            3.079607843137255
          ]
        },
        {
          "run": 9264,
          "values": [
            3.067578125
          ]
        },
        {
          "run": 9328,
          "values": [
            4.4874285714285715
          ]
        },
        {
          "run": 9392,
          "values": [
            3.043798449612403
          ]
        },
        {
          "run": 9456,
          "values": [
            3.0556420233463037
          ]
        }
      ],
      "system": [
        {
          "run": 9136,
          "values": [
            0.01
          ]
        },
        {
          "run": 9200,
          "values": [
            0.01
          ]
        },
        {
          "run": 9264,
          "values": [
            0.01
          ]
        },
        {
          "run": 9328,
          "values": [
            0.01
          ]
        },
        {
          "run": 9392,
          "values": [
            0.01
          ]
        },
        {
          "run": 9456,
          "values": [
            0.01
          ]
        }
      ],
      "user": [
        {
          "run": 9136,
          "values": [
            2.56
          ]
        },
        {
          "run": 9200,
          "values": [
            2.55
          ]
        },
        {
          "run": 9264,
          "values": [
            2.56
          ]
        },
        {
          "run": 9328,
          "values": [
            1.75
          ]
        },
        {
          "run": 9392,
          "values": [
            2.58
          ]
        },
        {
          "run": 9456,
          "values": [
            2.56
          ]
        }
      ]
    }
  },
  "gcc --hierarchical": {
    "execute": {
      "clocks": [
        {
          "run": 9084,
          "values": [
            7853
          ]
        },
        {
          "run": 9148,
          "values": [
            7853
          ]
        },
        {
          "run": 9212,
          "values": [
            7853
          ]
        },
        {
          "run": 9276,
          "values": [
            7853
          ]
        },
        {
          "run": 9340,
          "values": [
            7853
          ]
        },
        {
          "run": 9404,
          "values": [
            7853
          ]
        }
      ],
      "cpu": [
        {
          "run": 9084,
          "values": [
            2.59
          ]
        },
        {
          "run": 9148,
          "values": [
            2.56
          ]
        },
        {
          "run": 9212,
          "values": [
            2.59
          ]
        },
        {
          "run": 9276,
          "values": [
            2.61
          ]
        },
        {
          "run": 9340,
          "values": [
            2.57
          ]
        },
        {
          "run": 9404,
          "values": [
            2.56
          ]
        }
      ],
      "elapsed": [
        {
          "run": 9084,
          "values": [
            2.6
          ]
        },
        {
          "run": 9148,
          "values": [
            2.56
          ]
        },
        {
          "run": 9212,
          "values": [
            2.6
          ]
        },
        {
          "run": 9276,
          "values": [
            2.61
          ]
        },
        {
          "run": 9340,
          "values": [
            2.57
          ]
        },
        {
          "run": 9404,
          "values": [
            2.56
          ]
        }
      ],
      "memory": [
        {
          "run": 9084,
          "values": [
            13.344
          ]
        },
        {
          "run": 9148,
          "values": [
            13.38
          ]
        },
        {
          "run": 9212,
          "values": [
            13.424
          ]
        },
        {
          "run": 9276,
          "values": [
            13.488
          ]
        },
        {
          "run": 9340,
          "values": [
            13.456
          ]
        },
        {
          "run": 9404,
          "values": [
            13.376
          ]
        }
      ],
      "speed": [
        {
          "run": 9084,
          "values": [
            3.0203846153846152
          ]
        },
        {
          "run": 9148,
          "values": [
            3.067578125
          ]
        },
        {
          "run": 9212,
          "values": [
            3.0203846153846152
          ]
        },
        {
          "run": 9276,
          "values": [
            3.0088122605363985
          ]
        },
        {
          "run": 9340,
          "values": [
            3.0556420233463037
          ]
        },
        {
          "run": 9404,
          "values": [
            3.067578125
          ]
        }
      ],
      "system": [
        {
          "run": 9084,
          "values": [
            0.01
          ]
        },
        {
          "run": 9148,
          "values": [
            0.01
          ]
        },
        {
          "run": 9212,
          "values": [
            0.01
          ]
        },
        {
          "run": 9276,
          "values": [
            0.01
          ]
        },
        {
          "run": 9340,
          "values": [
            0.01
          ]
        },
        {
          "run": 9404,
          "values": [
            0.01
          ]
        }
      ],
      "user": [
        {
          "run": 9084,
          "values": [
            2.59
          ]
        },
        {
          "run": 9148,
          "values": [
            2.56
          ]
        },
        {
          "run": 9212,
          "values": [
            2.59
          ]
        },
        {
          "run": 9276,
          "values": [
            2.61
          ]
        },
        {
          "run": 9340,
          "values": [
            2.57
          ]
        },
        {
          "run": 9404,
          "values": [
            2.56
          ]
        }
      ]
    }
  }
}