{
  "clang --threads 4": {
    "execute": {
      "clocks": [
        {
          "run": 9096,
          "values": [
            873831
          ]
        },
        {
          "run": 9160,
          "values": [
            873831
          ]
        },
        {
          "run": 9224,
          "values": [
            873831
          ]
        }
      ],
      "cpu": [
        {
          "run": 9096,
          "values": [
            1884.88
          ]
        },
        {
          "run": 9160,
          "values": [
            1888.57
          ]
        },
        {
          "run": 9224,
          "values": [
            1878.5
          ]
        }
      ],
      "elapsed": [
        {
          "run": 9096,
          "values": [
            473.42
          ]
        },
        {
          "run": 9160,
          "values": [
            474.33
          ]
        },
        {
          "run": 9224,
          "values": [
            471.6
          ]
        }
      ],
      "memory": [
        {
          "run": 9096,
          "values": [
            44.368
          ]
        },
        {
          "run": 9160,
          "values": [
            44.144
          ]
        },
        {
          "run": 9224,
          "values": [
            44.428000000000004
          ]
        }
      ],
      "speed": [
        {
          "run": 9096,
          "values": [
            1.8457838705589118
          ]
        },
        {
          "run": 9160,
          "values": [
            1.8422427423945356
          ]
        },
        {
          "run": 9224,
          "values": [
            1.8529071246819337
          ]
        }
      ],
      "system": [
        {
          "run": 9096,
          "values": [
            0.47
          ]
        },
        {
          "run": 9160,
          "values": [
            0.54
          ]
        },
        {
          "run": 9224,
          "values": [
            0.41
          ]
        }
      ],
      "user": [
        {
          "run": 9096,
          "values": [
            1884.41
          ]
        },
        {
          "run": 9160,
          "values": [
            1888.03
          ]
        },
        {
          "run": 9224,
          "values": [
            1878.09
          ]
        }
      ]
    }
  },
  "gcc": {
    "execute": {
      "clocks": [
        {
          "run": 9135,
          "values": [
            873831
          ]
        },
        {
          "run": 9199,
          "values": [
            873831
          ]
        },
        {
          "run": 9263,
          "values": [
            873831
          ]
        }
      ],
      "cpu": [
        {
          "run": 9135,
          "values": [
            1099.9599999999998
          ]
        },
        {
          "run": 9199,
          "values": [
            1104.59
          ]
        },
        {
          "run": 9263,
          "values": [
            1101.62
          ]
        }
      ],
      "elapsed": [
        {
          "run": 9135,
          "values": [
            1100.04
          ]
        },
        {
          "run": 9199,
          "values": [
            1104.68
          ]
        },
        {
          "run": 9263,
          "values": [
            1101.73
          ]
        }
      ],
      "memory": [
        {
          "run": 9135,
          "values": [
            38.576
          ]
        },
        {
          "run": 9199,
          "values": [
            38.664
          ]
        },
        {
          "run": 9263,
          "values": [
            38.708
          ]
        }
      ],
      "speed": [
        {
          "run": 9135,
          "values": [
            0.7943629322570088
          ]
        },
        {
          "run": 9199,
          "values": [
            0.7910263605750081
          ]
        },
        {
          "run": 9263,
          "values": [
            0.7931444183239088
          ]
        }
      ],
      "system": [
        {
          "run": 9135,
          "values": [
            0.1
          ]
        },
        {
          "run": 9199,
          "values": [
            0.08
          ]
        },
        {
          "run": 9263,
          "values": [
            0.12
          ]
        }
      ],
      "user": [
        {
          "run": 9135,
          "values": [
            1099.86
          ]
        },
        {
          "run": 9199,
          "values": [
            1104.51
          ]
        },
        {
          "run": 9263,
          "values": [
            1101.5
          ]
        }
      ]
    }
  }
}